webtap/VISION.md
webtap/__init__.py
webtap/__main__.py
webtap/app.py
webtap/client.py
webtap/daemon.py
webtap/filters.py
webtap/notices.py
webtap/targets.py
webtap/api/__init__.py
webtap/api/app.py
webtap/api/server.py
webtap/api/sse.py
webtap/api/state.py
webtap/cdp/README.md
webtap/cdp/__init__.py
webtap/cdp/har.py
webtap/cdp/session.py
webtap/cdp/schema/README.md
webtap/cdp/schema/cdp_protocol.json
webtap/cdp/schema/cdp_version.json
webtap/commands/DEVELOPER_GUIDE.md
webtap/commands/TIPS.md
webtap/commands/__init__.py
webtap/commands/_builders.py
webtap/commands/_code_generation.py
webtap/commands/_tips.py
webtap/commands/_utils.py
webtap/commands/connection.py
webtap/commands/console.py
webtap/commands/entry.py
webtap/commands/extension.py
webtap/commands/fetch.py
webtap/commands/filters.py
webtap/commands/javascript.py
webtap/commands/launch.py
webtap/commands/navigation.py
webtap/commands/network.py
webtap/commands/quicktype.py
webtap/commands/request.py
webtap/commands/selections.py
webtap/commands/setup.py
webtap/commands/to_model.py
webtap/extension/background.js
webtap/extension/bind.js
webtap/extension/client.js
webtap/extension/datatable.js
webtap/extension/main.js
webtap/extension/manifest.json
webtap/extension/sidepanel.css
webtap/extension/sidepanel.html
webtap/extension/assets/icon-128.png
webtap/extension/assets/icon-16.png
webtap/extension/assets/icon-32.png
webtap/extension/assets/icon-48.png
webtap/extension/controllers/console.js
webtap/extension/controllers/filters.js
webtap/extension/controllers/header.js
webtap/extension/controllers/intercept.js
webtap/extension/controllers/network.js
webtap/extension/controllers/notices.js
webtap/extension/controllers/pages.js
webtap/extension/controllers/selections.js
webtap/extension/controllers/tabs.js
webtap/extension/controllers/targets.js
webtap/extension/controllers/theme.js
webtap/extension/lib/ui.js
webtap/extension/lib/utils.js
webtap/extension/lib/rpc/errors.js
webtap_tool-0.14.1.dist-info/METADATA
webtap_tool-0.14.1.dist-info/WHEEL
webtap_tool-0.14.1.dist-info/entry_points.txt
webtap_tool-0.14.1.dist-info/RECORD
