Metadata-Version: 2.4
Name: webtap-tool
Version: 0.14.1
Summary: Terminal-based web page inspector for AI debugging sessions
Author-email: Fredrik Angelsen <fredrikangelsen@gmail.com>
Classifier: Development Status :: 3 - Alpha
Classifier: Operating System :: MacOS :: MacOS X
Classifier: Operating System :: POSIX :: Linux
Classifier: Programming Language :: Python :: 3.12
Classifier: Topic :: Internet :: WWW/HTTP :: Browsers
Classifier: Topic :: Software Development :: Debuggers
Requires-Python: >=3.12
Requires-Dist: beautifulsoup4>=4.13.5
Requires-Dist: cryptography>=45.0.6
Requires-Dist: datamodel-code-generator>=0.35.0
Requires-Dist: duckdb>=1.3.2
Requires-Dist: fastapi>=0.116.1
Requires-Dist: httpx>=0.28.1
Requires-Dist: lxml>=6.0.1
Requires-Dist: msgpack-python>=0.5.6
Requires-Dist: platformdirs>=4.4.0
Requires-Dist: protobuf>=6.32.0
Requires-Dist: pyjwt>=2.10.1
Requires-Dist: pyyaml>=6.0.2
Requires-Dist: replkit2[all]>=0.12.0
Requires-Dist: transitions>=0.9.3
Requires-Dist: uvicorn>=0.35.0
Requires-Dist: websocket-client>=1.8.0
